vollib/__init__.py
vollib/black/__init__.py
vollib/black/greeks/__init__.py
vollib/black/greeks/analytical.py
vollib/black/greeks/numerical.py
vollib/black/implied_volatility.py
vollib/black_scholes/__init__.py
vollib/black_scholes/greeks/__init__.py
vollib/black_scholes/greeks/analytical.py
vollib/black_scholes/greeks/numerical.py
vollib/black_scholes/implied_volatility.py
vollib/black_scholes_merton/__init__.py
vollib/black_scholes_merton/greeks/__init__.py
vollib/black_scholes_merton/greeks/analytical.py
vollib/black_scholes_merton/greeks/numerical.py
vollib/black_scholes_merton/implied_volatility.py
vollib/helpers/__init__.py
vollib/helpers/constants.py
vollib/helpers/distributions.py
vollib/helpers/doctest_helper.py
vollib/helpers/exceptions.py
vollib/helpers/numerical_greeks.py
vollib/lets_be_rational/__init__.py
vollib/lets_be_rational/constants.py
vollib/lets_be_rational/core.py
vollib/lets_be_rational/exceptions.py
vollib/ref_python/__init__.py
vollib/ref_python/black/__init__.py
vollib/ref_python/black/greeks/__init__.py
vollib/ref_python/black/greeks/analytical.py
vollib/ref_python/black/greeks/numerical.py
vollib/ref_python/black/implied_volatility.py
vollib/ref_python/black_scholes/__init__.py
vollib/ref_python/black_scholes/greeks/__init__.py
vollib/ref_python/black_scholes/greeks/analytical.py
vollib/ref_python/black_scholes/greeks/numerical.py
vollib/ref_python/black_scholes/implied_volatility.py
vollib/ref_python/black_scholes_merton/__init__.py
vollib/ref_python/black_scholes_merton/greeks/__init__.py
vollib/ref_python/black_scholes_merton/greeks/analytical.py
vollib/ref_python/black_scholes_merton/greeks/numerical.py
vollib/ref_python/black_scholes_merton/implied_volatility.py
vollib_test-1.0.5.dist-info/LICENSE
vollib_test-1.0.5.dist-info/METADATA
vollib_test-1.0.5.dist-info/WHEEL
vollib_test-1.0.5.dist-info/RECORD
