Metadata-Version: 2.1
Name: vollib-test
Version: 1.0.5
Summary: Python library for calculating option prices, implied volatility and greeks.
Home-page: http://vollib.org
License: MIT
Author: vollib
Author-email: vollib@gammoncap.com
Requires-Python: >=3.9,<4.0
Classifier: License :: OSI Approved :: MIT License
Classifier: Programming Language :: Python :: 3
Classifier: Programming Language :: Python :: 3.9
Classifier: Programming Language :: Python :: 3.10
Classifier: Programming Language :: Python :: 3.11
Classifier: Programming Language :: Python :: 3.12
Classifier: Programming Language :: Python :: 3.13
Requires-Dist: cody-special (>=1.0.0,<2.0.0)
Requires-Dist: numpy (>=1.20,<2.0)
Requires-Dist: pandas (>=2.0,<3.0)
Requires-Dist: piecewise-rational (>=1.0.0,<2.0.0)
Requires-Dist: scipy (>=1.10,<2.0)
Requires-Dist: simplejson (>=3.0,<4.0)
Project-URL: Repository, https://github.com/vollib/vollib
